sharks/__init__.py
sharks-1.0.2.dist-info/LICENCE
sharks-1.0.2.dist-info/METADATA
sharks-1.0.2.dist-info/WHEEL
sharks-1.0.2.dist-info/top_level.txt
sharks-1.0.2.dist-info/RECORD
