Metadata-Version: 2.1
Name: sharks
Version: 1.0.2
Summary: A Python package for data analysis.
Home-page: https://github.com/Shashideep83/shark_lib
Author: Shashi Deep Dulam
Author-email: shashidulam83@gmail.com
License: MIT
Platform: UNKNOWN
Classifier: License :: OSI Approved :: MIT License
Classifier: Programming Language :: Python :: 3
Classifier: Programming Language :: Python :: 3.7
Requires-Dist: numpy
